eks_infra_mcp/__init__.py
eks_infra_mcp/server.py
eks_infra_mcp-0.1.5.dist-info/METADATA
eks_infra_mcp-0.1.5.dist-info/WHEEL
eks_infra_mcp-0.1.5.dist-info/entry_points.txt
eks_infra_mcp-0.1.5.dist-info/top_level.txt
eks_infra_mcp-0.1.5.dist-info/RECORD
