Metadata-Version: 2.4
Name: eks-infra-mcp
Version: 0.1.5
Summary: An MCP server exposing EKS infrastructure details
Author: Harman Singh Datta
Requires-Python: >=3.10
Requires-Dist: boto3
Requires-Dist: mcp
